tempmon/__init__.py
tempmon/daemon.py
tempmon/db.py
tempmon/migrate.py
tempmon-0.6.0.dist-info/DESCRIPTION.rst
tempmon-0.6.0.dist-info/entry_points.txt
tempmon-0.6.0.dist-info/METADATA
tempmon-0.6.0.dist-info/metadata.json
tempmon-0.6.0.dist-info/pbr.json
tempmon-0.6.0.dist-info/RECORD
tempmon-0.6.0.dist-info/top_level.txt
tempmon-0.6.0.dist-info/WHEEL
