Metadata-Version: 2.0
Name: tempmon
Version: 0.6.0
Summary: Temperature Monitoring Daemon
Home-page: https://pypi.python.org/pypi
Author: Doug Hellmann
Author-email: doug@doughellmann.com
License: UNKNOWN
Platform: UNKNOWN
Classifier: Development Status :: 4 - Beta
Classifier: Environment :: Console
Classifier: Intended Audience :: Information Technology
Classifier: Intended Audience :: System Administrators
Classifier: License :: OSI Approved :: Apache Software License
Classifier: Operating System :: POSIX :: Linux
Classifier: Programming Language :: Python
Classifier: Programming Language :: Python :: 2
Classifier: Programming Language :: Python :: 2.7
Requires-Dist: temperusb (>=1.2.3)
Requires-Dist: plotly (>=1.6.13)
Requires-Dist: PyYAML (>=3.11)
Requires-Dist: yweather (>=0.1)
